userWelcome/__init__.py
userWelcome/user.py
userWelcome-0.0.7.dist-info/METADATA
userWelcome-0.0.7.dist-info/WHEEL
userWelcome-0.0.7.dist-info/top_level.txt
userWelcome-0.0.7.dist-info/RECORD
