Metadata-Version: 2.1
Name: userWelcome
Version: 0.0.7
Summary: Simple python program with sql db
Author: Dan Litviniuc & Matteo Breganni
Author-email: <d.litviniuc@campus.unimib.it>
Keywords: python
Requires-Dist: astroid ==2.15.8
Requires-Dist: bandit ==1.7.5
Requires-Dist: beautifulsoup4 ==4.12.2
Requires-Dist: bs4 ==0.0.1
Requires-Dist: certifi ==2023.7.22
Requires-Dist: charset-normalizer ==3.3.0
Requires-Dist: colorama ==0.4.6
Requires-Dist: dill ==0.3.7
Requires-Dist: dodgy ==0.2.1
Requires-Dist: flake8 ==5.0.4
Requires-Dist: flake8-polyfill ==1.0.2
Requires-Dist: gitdb ==4.0.10
Requires-Dist: GitPython ==3.1.37
Requires-Dist: idna ==3.4
Requires-Dist: iniconfig ==2.0.0
Requires-Dist: isort ==5.12.0
Requires-Dist: lazy-object-proxy ==1.9.0
Requires-Dist: markdown-it-py ==3.0.0
Requires-Dist: mccabe ==0.7.0
Requires-Dist: mdurl ==0.1.2
Requires-Dist: mysql-connector-python ==8.1.0
Requires-Dist: packaging ==23.2
Requires-Dist: pbr ==5.11.1
Requires-Dist: pep8-naming ==0.10.0
Requires-Dist: platformdirs ==3.11.0
Requires-Dist: pluggy ==1.3.0
Requires-Dist: prospector ==1.10.2
Requires-Dist: protobuf ==4.21.12
Requires-Dist: pycodestyle ==2.9.1
Requires-Dist: pydocstyle ==6.3.0
Requires-Dist: pyflakes ==2.5.0
Requires-Dist: Pygments ==2.16.1
Requires-Dist: pylint ==2.17.7
Requires-Dist: pylint-celery ==0.3
Requires-Dist: pylint-django ==2.5.3
Requires-Dist: pylint-flask ==0.6
Requires-Dist: pylint-plugin-utils ==0.7
Requires-Dist: pytest ==7.4.2
Requires-Dist: PyYAML ==6.0.1
Requires-Dist: requests ==2.31.0
Requires-Dist: requirements-detector ==1.2.2
Requires-Dist: rich ==13.6.0
Requires-Dist: semver ==3.0.2
Requires-Dist: setoptconf-tmp ==0.3.1
Requires-Dist: smmap ==5.0.1
Requires-Dist: snowballstemmer ==2.2.0
Requires-Dist: soupsieve ==2.5
Requires-Dist: stevedore ==5.1.0
Requires-Dist: toml ==0.10.2
Requires-Dist: tomlkit ==0.12.1
Requires-Dist: urllib3 ==2.0.6
Requires-Dist: wrapt ==1.15.0
